Metadata-Version: 2.4
Name: mseep-crypto-pegmon-mcp
Version: 0.1.1
Summary: An MCP server that tracks stablecoin peg integrity across multiple blockchains
Author-email: mseep <support@skydeck.ai>
Requires-Python: >=3.10
License-File: LICENSE
Requires-Dist: mcp[cli]>=1.7.1
Requires-Dist: pandas>=2.2.3
Requires-Dist: pycoingecko>=3.2.0
Requires-Dist: tabulate>=0.9.0
Dynamic: license-file
